flask_social_login/__init__.py
flask_social_login/core.py
flask_social_login/datastore.py
flask_social_login/utils.py
flask_social_login/views.py
flask_social_login/providers/__init__.py
flask_social_login/providers/facebook.py
flask_social_login/providers/google.py
flask_social_login-0.2.2.dist-info/AUTHORS.rst
flask_social_login-0.2.2.dist-info/LICENSE
flask_social_login-0.2.2.dist-info/METADATA
flask_social_login-0.2.2.dist-info/WHEEL
flask_social_login-0.2.2.dist-info/top_level.txt
flask_social_login-0.2.2.dist-info/RECORD
