Metadata-Version: 2.1
Name: flask-social-login
Version: 0.2.2
Summary: OAuth Provider integration for Flask-Login
Home-page: https://github.com/yoophi/flask_social_login
Author: Pyunghyuk Yoo
Author-email: yoophi@gmail.com
License: MIT license
Keywords: flask_social_login
Platform: UNKNOWN
Classifier: Development Status :: 2 - Pre-Alpha
Classifier: Intended Audience :: Developers
Classifier: License :: OSI Approved :: MIT License
Classifier: Natural Language :: English
Classifier: Programming Language :: Python :: 3
Classifier: Programming Language :: Python :: 3.5
Classifier: Programming Language :: Python :: 3.6
Classifier: Programming Language :: Python :: 3.7
Classifier: Programming Language :: Python :: 3.8
Requires-Python: >=3.5
Requires-Dist: Flask (==1.1.2)
Requires-Dist: Flask-Login (==0.5.0)
Requires-Dist: Flask-OAuthlib (==0.9.6)
Requires-Dist: facebook-sdk (==3.1.0)
Requires-Dist: httplib2 (==0.18.1)
Requires-Dist: apiclient (==1.0.4)
Requires-Dist: oauth2client (==4.1.3)
Requires-Dist: google-api-python-client (==1.12.8)
